simple_settings/__init__.py
simple_settings/constants.py
simple_settings/core.py
simple_settings/special_settings.py
simple_settings/utils.py
simple_settings/dynamic_settings/__init__.py
simple_settings/dynamic_settings/base.py
simple_settings/dynamic_settings/consul_reader.py
simple_settings/dynamic_settings/database_reader.py
simple_settings/dynamic_settings/memcached_reader.py
simple_settings/dynamic_settings/redis_reader.py
simple_settings/dynamic_settings/s3_reader.py
simple_settings/strategies/__init__.py
simple_settings/strategies/cfg.py
simple_settings/strategies/environ.py
simple_settings/strategies/json_file.py
simple_settings/strategies/python.py
simple_settings/strategies/toml_file.py
simple_settings/strategies/yaml_file.py
simple_settings-1.1.0.dist-info/LICENSE
simple_settings-1.1.0.dist-info/METADATA
simple_settings-1.1.0.dist-info/WHEEL
simple_settings-1.1.0.dist-info/top_level.txt
simple_settings-1.1.0.dist-info/RECORD
