Metadata-Version: 2.1
Name: simple-settings
Version: 1.1.0
Summary: A simple way to manage your project settings
Home-page: https://github.com/drgarcia1986/simple-settings
Author: Diego Garcia
Author-email: drgarcia1986@gmail.com
License: UNKNOWN
Download-URL: https://github.com/drgarcia1986/simple-settings/tarball/master
Keywords: django flask bottle tornado settings configuration conf
Platform: UNKNOWN
Classifier: Intended Audience :: Developers
Classifier: License :: OSI Approved :: MIT License
Classifier: Operating System :: OS Independent
Classifier: Programming Language :: Python :: 2
Classifier: Programming Language :: Python :: 3
License-File: LICENSE
Provides-Extra: all
Requires-Dist: SQLAlchemy (==1.4.26) ; extra == 'all'
Requires-Dist: redis (==3.5.3) ; extra == 'all'
Requires-Dist: jsonpickle (==2.0.0) ; extra == 'all'
Requires-Dist: PyYAML (==6.0) ; extra == 'all'
Requires-Dist: pymemcache (==3.5.0) ; extra == 'all'
Requires-Dist: toml (==0.10.2) ; extra == 'all'
Requires-Dist: boto3 (==1.9.201) ; extra == 'all'
Requires-Dist: consulate (==0.6.0) ; extra == 'all'
Requires-Dist: six (==1.16.0) ; extra == 'all'
Provides-Extra: consul
Requires-Dist: consulate (==0.6.0) ; extra == 'consul'
Requires-Dist: jsonpickle (==2.0.0) ; extra == 'consul'
Provides-Extra: database
Requires-Dist: SQLAlchemy (==1.4.26) ; extra == 'database'
Requires-Dist: jsonpickle (==2.0.0) ; extra == 'database'
Provides-Extra: memcached
Requires-Dist: pymemcache (==3.5.0) ; extra == 'memcached'
Requires-Dist: six (==1.16.0) ; extra == 'memcached'
Requires-Dist: jsonpickle (==2.0.0) ; extra == 'memcached'
Provides-Extra: redis
Requires-Dist: redis (==3.5.3) ; extra == 'redis'
Requires-Dist: six (==1.16.0) ; extra == 'redis'
Requires-Dist: jsonpickle (==2.0.0) ; extra == 'redis'
Provides-Extra: s3
Requires-Dist: boto3 (==1.9.201) ; extra == 's3'
Requires-Dist: jsonpickle (==2.0.0) ; extra == 's3'
Provides-Extra: toml
Requires-Dist: toml (==0.10.2) ; extra == 'toml'
Provides-Extra: yaml
Requires-Dist: PyYAML (==6.0) ; extra == 'yaml'
